zadeh/__init__.py
zadeh/context.py
zadeh/domains.py
zadeh/fis.py
zadeh/mparser.py
zadeh/rules.py
zadeh/server.py
zadeh/sets.py
zadeh/tune.py
zadeh/variables.py
zadeh-0.3.0.dist-info/LICENSE.txt
zadeh-0.3.0.dist-info/METADATA
zadeh-0.3.0.dist-info/WHEEL
zadeh-0.3.0.dist-info/entry_points.txt
zadeh-0.3.0.dist-info/top_level.txt
zadeh-0.3.0.dist-info/RECORD
