Metadata-Version: 2.1
Name: zadeh
Version: 0.3.0
Summary: Python package to build fuzzy inference systems
Home-page: https://github.com/dih5/zadeh
Author: Dih5
Author-email: dihedralfive@gmail.com
License: UNKNOWN
Platform: UNKNOWN
Classifier: Development Status :: 3 - Alpha
Classifier: Intended Audience :: Science/Research
Classifier: Natural Language :: English
Classifier: Programming Language :: Python :: 3
Classifier: Programming Language :: Python :: 3.5
Classifier: Programming Language :: Python :: 3.6
Classifier: Programming Language :: Python :: 3.7
Classifier: Programming Language :: Python :: 3.8
License-File: LICENSE.txt
Requires-Dist: numpy
Provides-Extra: docs
Requires-Dist: nbsphinx ; extra == 'docs'
Requires-Dist: sphinx-rtd-theme ; extra == 'docs'
Requires-Dist: IPython ; extra == 'docs'
Provides-Extra: extras
Requires-Dist: matplotlib ; extra == 'extras'
Requires-Dist: ipywidgets ; extra == 'extras'
Requires-Dist: jinja2 ; extra == 'extras'
Provides-Extra: server
Requires-Dist: flask ; extra == 'server'
Requires-Dist: flask-restx ; extra == 'server'
Provides-Extra: test
Requires-Dist: pytest ; extra == 'test'
